{
    "title": "Canada Higher Education House",
    "description": "A site for researching and applying for scholarships in canada",
    "heading": "Your Programs",
    "provinceSearchHeading": "Programs in: _{province}_",
    "universitySearchHeading": "Programs at: _{university}_",
    "nameSearchHeading": "Programs involving: _{name}_",
    "cards": {
        "tuitionInfomation": "Tuition",
        "domestic": "Domestic:",
        "international": "International:",
        "saveProgram": "Save",
        "unSaveProgram": "Forget",
        "moreInfo": "Details"
    },
    "noResults": {
        "heading": "We could not find any programs for that search",
        "body": "Please try another search!"
    },
    "overQuota": {
        "heading": "You have exceeded your monthly quota",
        "memberBody": "You only have 30 searches per month. <a href=\"#\" data-modal=\"membershipModal\">Become a member</a> to access unlimited results",
        "visitorBody": "You only have 3 searches per month. <a href=\"#\" data-modal=\"signUpModal\">Join</a> to get 30 searches per month. If you also choose to buy a full membership, you will get unlimited searches and all the other perks of full memerbship."
    },
    "pagination": {
        "results": "Results",
        "divider": "-",
        "of": "of",
        "memberPlug": {
            "notSignedIn": "<a href=\"#\" data-modal=\"signUpModal\">Join</a> or <a href=\"#\" data-modal=\"loginModal\">sign in</a> and become a member to access more results",
            "isSignedIn": "<a href=\"#\" data-modal=\"membershipModal\">Become a member</a> to access more results"
        }
    }
}
