{
    "title": "Canada Higher Education House",
    "description": "A site for researching and applying for scholarships in canada",
    "heading": "Scholarship Applications",
    "calendar": {
        "start": {
            "id": "scholarshipApplicationListcalendarStart",
            "label": "Show applications after:",
            "placeholder": "Date",
            "otherId": "scholarshipApplicationListcalendarEnd",
            "type": "date"
        },
        "end": {
            "id": "scholarshipApplicationListcalendarEnd",
            "label": "Show applications before:",
            "placeholder": "Date",
            "otherId": "scholarshipApplicationListcalendarStart",
            "type": "date"
        }
    },
    "searchBar": {
        "id": "applicationsListingNameSearch",
        "placeholder": "Filter By Name"
    }
}
